{
  "version": 3,
  "middleware": {
    "/": {
      "files": [
        "server/edge/chunks/_0d3699dc._.js",
        "server/edge/chunks/[root-of-the-server]__dc15d093._.js",
        "server/edge/chunks/edge-wrapper_594fdf6a.js"
      ],
      "name": "middleware",
      "page": "/",
      "matchers": [
        {
          "regexp": "^(?:\\/(_next\\/data\\/[^/]{1,}))?\\/admin(?:\\/((?:[^\\/#\\?]+?)(?:\\/(?:[^\\/#\\?]+?))*))?(\\\\.json)?[\\/#\\?]?$",
          "originalSource": "/admin/:path*"
        },
        {
          "regexp": "^(?:\\/(_next\\/data\\/[^/]{1,}))?\\/member_control(?:\\/((?:[^\\/#\\?]+?)(?:\\/(?:[^\\/#\\?]+?))*))?(\\\\.json)?[\\/#\\?]?$",
          "originalSource": "/member_control/:path*"
        },
        {
          "regexp": "^(?:\\/(_next\\/data\\/[^/]{1,}))?(?:\\/((?!api|_next\\/static|_next\\/image|favicon.ico).*))(\\\\.json)?[\\/#\\?]?$",
          "originalSource": "/((?!api|_next/static|_next/image|favicon.ico).*)"
        }
      ],
      "wasm": [],
      "assets": [],
      "env": {
        "__NEXT_BUILD_ID": "development",
        "NEXT_SERVER_ACTIONS_ENCRYPTION_KEY": "8RxSvYcENLC+2YBnG2YI80xtS/upGLolgnuBwC34+SY=",
        "__NEXT_PREVIEW_MODE_ID": "cbbe88169b517c8581d4fd13719ae87c",
        "__NEXT_PREVIEW_MODE_ENCRYPTION_KEY": "33087874046e64812a689e8d99307694da826ce73bf4c0d9d45822d72884ec2b",
        "__NEXT_PREVIEW_MODE_SIGNING_KEY": "ee50f766c762a292b757dee02de85c348b53f68add8e30b253b726a00d3893b9"
      }
    }
  },
  "sortedMiddleware": [
    "/"
  ],
  "functions": {}
}